git_stats_all.py
setup.py
git_stats_all.egg-info/PKG-INFO
git_stats_all.egg-info/SOURCES.txt
git_stats_all.egg-info/dependency_links.txt
git_stats_all.egg-info/entry_points.txt
git_stats_all.egg-info/pbr.json
git_stats_all.egg-info/requires.txt
git_stats_all.egg-info/top_level.txt