Metadata-Version: 1.0
Name: git-stats-all
Version: 0.0.1
Summary: Imports all your git projects using 'git-stats-importer'
Home-page: https://github.com/arruda/git-stats-all
Author: Felipe Arruda Pontes
Author-email: contato@arruda.blog.br
License: MIT
Keywords: git-stats,git-stats-importer,git-stats-all
Platform: UNKNOWN
